[
  {
    "component": "APA-106-F5",
    "type": "LED",
    "pins": [
      "DO",
      "GND",
      "VDD",
      "DI"
    ],
    "description": "RGB LED with integrated controller, 5mm Package",
    "keywords": [
      "RGB",
      "LED",
      "addressable",
      "8bit",
      "pwm",
      "5bit",
      "greyscale"
    ]
  },
  {
    "component": "APA102",
    "type": "LED",
    "pins": [
      "DI",
      "CI",
      "GND",
      "VCC",
      "CO",
      "DO"
    ],
    "description": "RGB LED with integrated controller",
    "keywords": [
      "RGB",
      "LED",
      "addressable",
      "8bit",
      "pwm",
      "5bit",
      "greyscale"
    ]
  },
  {
    "component": "APA102-2020",
    "type": "LED",
    "pins": [
      "VDD",
      "CKO",
      "SDO",
      "SDI",
      "CKI",
      "GND"
    ],
    "description": "RGB LED with integrated controller",
    "keywords": [
      "RGB",
      "LED",
      "addressable",
      "8bit",
      "pwm",
      "5bit",
      "greyscale"
    ]
  },
  {
    "component": "APFA3010",
    "type": "LED",
    "pins": [
      "R",
      "A",
      "G",
      "B"
    ],
    "description": "LED RGB, Common Anode, SMD, 3.0x1.5mm, Horizontal",
    "keywords": [
      "LED",
      "RGB",
      "SMD",
      "Kingbright",
      "APFA3010",
      "Horizontal"
    ]
  },
  {
    "component": "ASMB-MTB0-0A3A2",
    "type": "LED",
    "pins": [
      "A",
      "BK",
      "GK",
      "RK"
    ],
    "description": "Tricolor Black Surface LED, Common Anode Pin 1, PLCC-4",
    "keywords": [
      "led",
      "rgb",
      "diode"
    ]
  },
  {
    "component": "ASMB-MTB1-0A3A2",
    "type": "LED",
    "pins": [
      "RK",
      "GK",
      "BK",
      "A"
    ],
    "description": "Tricolor Black Surface LED, Common Anode Pin 4, PLCC-4",
    "keywords": [
      "led",
      "rgb",
      "diode"
    ]
  },
  {
    "component": "ASMT-YTC2-0AA02",
    "type": "LED",
    "pins": [
      "KB",
      "KG",
      "KR",
      "AR",
      "AG",
      "AB"
    ],
    "description": "Triple LED RVB (Avago Technology)",
    "keywords": [
      "LED",
      "RGB"
    ]
  },
  {
    "component": "ASMT-YTB7-0AA02",
    "type": "LED",
    "pins": [
      "KB",
      "KG",
      "KR",
      "AR",
      "AG",
      "AB"
    ],
    "description": "Triple LED RVB (Avago Technology)",
    "keywords": [
      "LED",
      "RGB"
    ]
  },
  {
    "component": "CLS6B-FKW",
    "type": "LED",
    "pins": [
      "AB",
      "KB",
      "AR",
      "KR",
      "AG"
    ],
    "description": "Cree PLCC6 3 in 1 SMD LED, PLCC-6",
    "keywords": [
      "LED",
      "RGB"
    ]
  },
  {
    "component": "QLS6B-FKW",
    "type": "LED",
    "pins": [
      "AB",
      "KB",
      "AR",
      "KR",
      "AG"
    ],
    "description": "Cree PLCC6 3 in 1 SMD LED, PLCC-6",
    "keywords": [
      "LED",
      "RGB"
    ]
  },
  {
    "component": "CLV1L-FKB",
    "type": "LED",
    "pins": [
      "A",
      "RK",
      "GK",
      "BK"
    ],
    "description": "Cree PLCC4 3 in 1 SMD LED",
    "keywords": [
      "led",
      "rgb",
      "diode"
    ]
  },
  {
    "component": "HDSP-4830",
    "type": "LED",
    "pins": [
      "A",
      "K"
    ],
    "description": "10-element LED arrays, high effecient red",
    "keywords": [
      "display",
      "LED",
      "array"
    ]
  },
  {
    "component": "HDSP-4830_2",
    "type": "LED",
    "pins": [
      "A",
      "K"
    ],
    "description": "BAR GRAPH 10 segment block, high efficiency red",
    "keywords": [
      "display",
      "LED",
      "array"
    ]
  },
  {
    "component": "HDSP-4832",
    "type": "LED",
    "pins": [
      "A",
      "K"
    ],
    "description": "10-element LED arrays, Mix of high effecient red, yellow and green",
    "keywords": [
      "display",
      "LED",
      "array"
    ]
  },
  {
    "component": "HDSP-4832_2",
    "type": "LED",
    "pins": [
      "A",
      "K"
    ],
    "description": "BAR GRAPH 10 segment block, Mix of high efficiency red, yellow and green",
    "keywords": [
      "display",
      "LED",
      "array"
    ]
  },
  {
    "component": "HDSP-4836",
    "type": "LED",
    "pins": [
      "A",
      "K"
    ],
    "description": "10-element LED arrays, Mix of high effecient red, yellow and green",
    "keywords": [
      "display",
      "LED",
      "array"
    ]
  },
  {
    "component": "HDSP-4836_2",
    "type": "LED",
    "pins": [
      "A",
      "K"
    ],
    "description": "BAR GRAPH 10 segment block, Mix of high efficiency red, yellow and green",
    "keywords": [
      "display",
      "LED",
      "array"
    ]
  },
  {
    "component": "HDSP-4840",
    "type": "LED",
    "pins": [
      "A",
      "K"
    ],
    "description": "10-element LED arrays, Yellow",
    "keywords": [
      "display",
      "LED",
      "array"
    ]
  },
  {
    "component": "HDSP-4840_2",
    "type": "LED",
    "pins": [
      "A",
      "K"
    ],
    "description": "BAR GRAPH 10 segment block, yellow",
    "keywords": [
      "display",
      "LED",
      "array"
    ]
  },
  {
    "component": "HDSP-4850",
    "type": "LED",
    "pins": [
      "A",
      "K"
    ],
    "description": "10-element LED arrays, Green",
    "keywords": [
      "display",
      "LED",
      "array"
    ]
  },
  {
    "component": "HDSP-4850_2",
    "type": "LED",
    "pins": [
      "A",
      "K"
    ],
    "description": "BAR GRAPH 10 segment block, green",
    "keywords": [
      "display",
      "LED",
      "array"
    ]
  },
  {
    "component": "HLCP-J100",
    "type": "LED",
    "pins": [
      "A",
      "K"
    ],
    "description": "10-element LED arrays, AIGaAs Red",
    "keywords": [
      "display",
      "LED",
      "array"
    ]
  },
  {
    "component": "HLCP-J100_2",
    "type": "LED",
    "pins": [
      "A",
      "K"
    ],
    "description": "BAR GRAPH 10 segment block, AlGaAs red",
    "keywords": [
      "display",
      "LED",
      "array"
    ]
  },
  {
    "component": "IR26-21C_L110_TR8",
    "type": "LED",
    "pins": [
      "K",
      "A"
    ],
    "description": "940nm, 20 deg, Infrared LED, 1206",
    "keywords": [
      "IR",
      "LED"
    ]
  },
  {
    "component": "IRL81A",
    "type": "LED",
    "pins": [
      "K",
      "A"
    ],
    "description": "850nm High Power Infrared Emitter, Side-Emitter package",
    "keywords": [
      "IR",
      "LED"
    ]
  },
  {
    "component": "Inolux_IN-PI554FCH",
    "type": "LED",
    "pins": [
      "VSS",
      "DIN",
      "VDD",
      "DO"
    ],
    "description": "5050 RGB LED 4-Pin with integrated IC",
    "keywords": [
      "RGB",
      "LED",
      "NeoPixel",
      "addressable"
    ]
  },
  {
    "component": "Inolux_IN-PI556FCH",
    "type": "LED",
    "pins": [
      "DO",
      "DIN",
      "VDD",
      "NC",
      "VCC",
      "VSS"
    ],
    "description": "5050 RGB LED 6-Pin with integrated IC",
    "keywords": [
      "RGB",
      "LED",
      "NeoPixel",
      "addressable"
    ]
  },
  {
    "component": "LD271",
    "type": "LED",
    "pins": [
      "K",
      "A"
    ],
    "description": "940nm IR-LED, 5mm",
    "keywords": [
      "IR",
      "LED"
    ]
  },
  {
    "component": "SFH4546",
    "type": "LED",
    "pins": [
      "K",
      "A"
    ],
    "description": "High-Power IR LED 940nm",
    "keywords": [
      "IR",
      "LED"
    ]
  },
  {
    "component": "CQY99",
    "type": "LED",
    "pins": [
      "K",
      "A"
    ],
    "description": "950nm IR-LED, 5mm",
    "keywords": [
      "IR",
      "LED"
    ]
  },
  {
    "component": "LD274",
    "type": "LED",
    "pins": [
      "K",
      "A"
    ],
    "description": "950nm IR-LED, 5mm",
    "keywords": [
      "IR",
      "LED"
    ]
  },
  {
    "component": "SFH4550",
    "type": "LED",
    "pins": [
      "K",
      "A"
    ],
    "description": "950nm High-Power IR-LED, 5mm",
    "keywords": [
      "IR",
      "LED"
    ]
  },
  {
    "component": "LED_Cree_XHP50_12V",
    "type": "LED",
    "pins": [
      "K",
      "A",
      "PAD"
    ],
    "description": "XLamp\u00ae XHP50 LED, 12V footprint (all 4 LEDs in series)",
    "keywords": [
      "led",
      "diode"
    ]
  },
  {
    "component": "LED_Cree_XHP50_6V",
    "type": "LED",
    "pins": [
      "K",
      "A",
      "PAD"
    ],
    "description": "XLamp\u00ae XHP50 LED, 6V footprint (2x2 serial LEDs in parallel)",
    "keywords": [
      "led",
      "diode"
    ]
  },
  {
    "component": "LED_Cree_XHP70_12V",
    "type": "LED",
    "pins": [
      "K",
      "A",
      "PAD"
    ],
    "description": "XLamp\u00ae XHP70 LED, 12V footprint (all 4 LEDs in series)",
    "keywords": [
      "led",
      "diode"
    ]
  },
  {
    "component": "LED_Cree_XHP70_6V",
    "type": "LED",
    "pins": [
      "K",
      "A",
      "PAD"
    ],
    "description": "XLamp\u00ae XHP70 LED, 6V footprint (2x2 serial LEDs in parallel)",
    "keywords": [
      "led",
      "diode"
    ]
  },
  {
    "component": "NeoPixel_THT",
    "type": "LED",
    "pins": [
      "DOUT",
      "GND",
      "VDD",
      "DIN"
    ],
    "description": "RGB LED with integrated controller, 5mm/8mm LED package",
    "keywords": [
      "RGB",
      "LED",
      "NeoPixel",
      "addressable"
    ]
  },
  {
    "component": "QLS6A-FKW",
    "type": "LED",
    "pins": [
      "AB",
      "KB",
      "AR",
      "KR",
      "AG"
    ],
    "description": "Cree PLCC6 3 in 1 SMD LED with zener protection, PLCC-6",
    "keywords": [
      "LED",
      "RGB"
    ]
  },
  {
    "component": "SFH4356P",
    "type": "LED",
    "pins": [
      "K",
      "A"
    ],
    "description": "Infrared LED , 3mm LED package",
    "keywords": [
      "opto",
      "IR",
      "LED"
    ]
  },
  {
    "component": "IR204A",
    "type": "LED",
    "pins": [
      "K",
      "A"
    ],
    "description": "Infrared LED , 3mm LED package",
    "keywords": [
      "opto",
      "IR",
      "LED"
    ]
  },
  {
    "component": "TSAL4400",
    "type": "LED",
    "pins": [
      "K",
      "A"
    ],
    "description": "Infrared LED , 3mm LED package",
    "keywords": [
      "opto",
      "IR",
      "LED"
    ]
  },
  {
    "component": "SFH4346",
    "type": "LED",
    "pins": [
      "K",
      "A"
    ],
    "description": "Infrared LED , 3mm LED package",
    "keywords": [
      "opto",
      "IR",
      "LED"
    ]
  },
  {
    "component": "SFH460",
    "type": "LED",
    "pins": [
      "K",
      "A"
    ],
    "description": "GaAlAs Infrared LED, TO-18 package",
    "keywords": [
      "opto",
      "IR",
      "LED"
    ]
  },
  {
    "component": "SFH482",
    "type": "LED",
    "pins": [
      "K",
      "A"
    ],
    "description": "GaAlAs Infrared LED (880 nm), TO-18 package",
    "keywords": [
      "opto",
      "IR",
      "LED"
    ]
  },
  {
    "component": "SFH480",
    "type": "LED",
    "pins": [
      "K",
      "A"
    ],
    "description": "GaAlAs Infrared LED (880 nm), TO-18 package",
    "keywords": [
      "IR",
      "LED",
      "Opto"
    ]
  },
  {
    "component": "SK6805",
    "type": "LED",
    "pins": [
      "DOUT",
      "VSS",
      "DIN",
      "VDD"
    ],
    "description": "RGB LED with integrated controller",
    "keywords": [
      "RGB",
      "LED",
      "NeoPixel",
      "Nano",
      "addressable"
    ]
  },
  {
    "component": "SK6812",
    "type": "LED",
    "pins": [
      "VSS",
      "DIN",
      "VDD",
      "DOUT"
    ],
    "description": "RGB LED with integrated controller",
    "keywords": [
      "RGB",
      "LED",
      "NeoPixel",
      "addressable"
    ]
  },
  {
    "component": "SK6812MINI",
    "type": "LED",
    "pins": [
      "DOUT",
      "VSS",
      "DIN",
      "VDD"
    ],
    "description": "RGB LED with integrated controller",
    "keywords": [
      "RGB",
      "LED",
      "NeoPixel",
      "Mini",
      "addressable"
    ]
  },
  {
    "component": "SMLVN6RGB",
    "type": "LED",
    "pins": [
      "BA",
      "RA",
      "GA",
      "GK",
      "RK",
      "BK"
    ],
    "description": "High Brightness Tri-Color LED, RGB, 3.5x2.8mm",
    "keywords": [
      "LED",
      "RGB",
      "Diode"
    ]
  },
  {
    "component": "WS2812B",
    "type": "LED",
    "pins": [
      "VDD",
      "DOUT",
      "VSS",
      "DIN"
    ],
    "description": "RGB LED with integrated controller",
    "keywords": [
      "RGB",
      "LED",
      "NeoPixel",
      "addressable"
    ]
  },
  {
    "component": "WS2812S",
    "type": "LED",
    "pins": [
      "DOUT",
      "DIN",
      "VCC",
      "NC",
      "VDD",
      "VSS"
    ],
    "description": "RGB LED with integrated controller",
    "keywords": [
      "RGB",
      "LED",
      "addressable"
    ]
  },
  {
    "component": "WS2812",
    "type": "LED",
    "pins": [
      "DOUT",
      "DIN",
      "VCC",
      "NC",
      "VDD",
      "VSS"
    ],
    "description": "RGB LED with integrated controller",
    "keywords": [
      "RGB",
      "LED",
      "NeoPixel",
      "addressable"
    ]
  },
  {
    "component": "WS2813",
    "type": "LED",
    "pins": [
      "VCC",
      "VDD",
      "DOUT",
      "DIN",
      "GND",
      "BIN"
    ],
    "description": "RGB LED with integrated controller",
    "keywords": [
      "RGB",
      "LED",
      "addressable"
    ]
  },
  {
    "component": "WS2822S",
    "type": "LED",
    "pins": [
      "DAI",
      "ADRI",
      "VCC",
      "GND",
      "ADRO",
      "VDD"
    ],
    "description": "RGB LED with integrated controller",
    "keywords": [
      "RGB",
      "LED",
      "addressable"
    ]
  }
]